alignai/__init__.py
alignai/api_client.py
alignai/buffer_storage.py
alignai/client.py
alignai/config.py
alignai/constants.py
alignai/exception.py
alignai/integration/langchain.py
alignai/integration/llama_index.py
alignai/logger.py
alignai/proto/__init__.py
alignai/proto/ingestion/v1alpha/__init__.py
alignai/proto/ingestion/v1alpha/event_pb2.py
alignai/proto/ingestion/v1alpha/event_pb2.pyi
alignai/proto/ingestion/v1alpha/ingestion_pb2.py
alignai/proto/ingestion/v1alpha/ingestion_pb2.pyi
alignai/utils.py
alignai/validate.py
alignai/worker.py
alignai-0.3.2.dist-info/LICENSE
alignai-0.3.2.dist-info/METADATA
alignai-0.3.2.dist-info/WHEEL
alignai-0.3.2.dist-info/RECORD
