Metadata-Version: 2.1
Name: alignai
Version: 0.3.2
Summary: Python SDK for Align AI
Author: Coxwave
Author-email: tech@coxwave.com
Requires-Python: >=3.9.0,<4.0
Classifier: Programming Language :: Python :: 3
Classifier: Programming Language :: Python :: 3.9
Classifier: Programming Language :: Python :: 3.10
Classifier: Programming Language :: Python :: 3.11
Classifier: Programming Language :: Python :: 3.12
Classifier: Programming Language :: Python :: 3.13
Requires-Dist: googleapis-common-protos (>=1.65.0,<2.0.0)
Requires-Dist: protobuf (>=4.25.3,<6.0.0)
Requires-Dist: requests (>=2.31.0,<3.0.0)
